{
  "country": "US",
  "countryName": "United States",
  "generatedAt": "2026-05-09T02:27:00.880430Z",
  "windowHours": 24,
  "windowStartOffsetHours": 4,
  "premiumSportsOnly": true,
  "sourceGuides": [
    "data/normalized/guide-premium-US-tvtv.us.xml",
    "data/normalized/guide-premium-US-tvguide.com.xml"
  ],
  "channelCount": 9,
  "channels": [
    {
      "id": "FoxSports1.us",
      "name": "FOX Sports 1",
      "logoUrl": "https://i.imgur.com/O9BapV9.png",
      "provider": "TV Guide US sports guide",
      "providerKey": "premium-tvguide-us",
      "sources": [
        "data/normalized/guide-premium-US-tvguide.com.xml"
      ],
      "currentProgram": {
        "title": "Indycar INXT Racing",
        "subtitle": null,
        "description": "from Indianapolis Motor Speedway Road Course",
        "categories": [],
        "sportType": "Motorsport",
        "competition": null,
        "imageUrl": null,
        "startAt": "2026-05-09T02:00:00Z",
        "endAt": "2026-05-09T03:00:00Z"
      },
      "programs": [
        {
          "title": "NASCAR Craftsman Truck Series",
          "subtitle": null,
          "description": "from Watkins Glen International in Watkins Glen, N.Y.",
          "categories": [],
          "sportType": "Motorsport",
          "competition": null,
          "imageUrl": null,
          "startAt": "2026-05-08T20:30:00Z",
          "endAt": "2026-05-08T23:30:00Z"
        },
        {
          "title": "Bobby Rahal: True American Racer",
          "subtitle": null,
          "description": null,
          "categories": [],
          "sportType": null,
          "competition": null,
          "imageUrl": null,
          "startAt": "2026-05-08T23:30:00Z",
          "endAt": "2026-05-09T00:30:00Z"
        },
        {
          "title": "Indycar NICS Qualifications",
          "subtitle": null,
          "description": "from Indianapolis Motor Speedway Road Course",
          "categories": [],
          "sportType": "Motorsport",
          "competition": null,
          "imageUrl": null,
          "startAt": "2026-05-09T00:30:00Z",
          "endAt": "2026-05-09T02:00:00Z"
        },
        {
          "title": "Indycar INXT Racing",
          "subtitle": null,
          "description": "from Indianapolis Motor Speedway Road Course",
          "categories": [],
          "sportType": "Motorsport",
          "competition": null,
          "imageUrl": null,
          "startAt": "2026-05-09T02:00:00Z",
          "endAt": "2026-05-09T03:00:00Z"
        },
        {
          "title": "NASCAR Craftsman Truck Series",
          "subtitle": null,
          "description": "from Watkins Glen International in Watkins Glen, N.Y.",
          "categories": [],
          "sportType": "Motorsport",
          "competition": null,
          "imageUrl": null,
          "startAt": "2026-05-09T03:00:00Z",
          "endAt": "2026-05-09T04:00:00Z"
        },
        {
          "title": "TMZ Sports",
          "subtitle": null,
          "description": "Covering gossip, scandal and the everyday lives of athletes in professional and college sports, the crew comically highlights exclusive footage of the superstars spotted around Hollywood, New York Cit",
          "categories": [
            "News"
          ],
          "sportType": null,
          "competition": null,
          "imageUrl": null,
          "startAt": "2026-05-09T04:00:00Z",
          "endAt": "2026-05-09T04:30:00Z"
        },
        {
          "title": "TMZ Sports Weekend",
          "subtitle": null,
          "description": "The biggest sports stories and rumors of the week are covered, as the analysts break down the news surrounding each of the headlines to discuss how those involved will be impacted, along with guest in",
          "categories": [],
          "sportType": null,
          "competition": null,
          "imageUrl": null,
          "startAt": "2026-05-09T04:30:00Z",
          "endAt": "2026-05-09T05:00:00Z"
        },
        {
          "title": "UFL Football",
          "subtitle": null,
          "description": "Columbus Aviators at St. Louis Battlehawks from The Dome at America's Center",
          "categories": [],
          "sportType": "Football",
          "competition": null,
          "imageUrl": null,
          "startAt": "2026-05-09T05:00:00Z",
          "endAt": "2026-05-09T08:00:00Z"
        },
        {
          "title": "TMZ Sports",
          "subtitle": null,
          "description": "Covering gossip, scandal and the everyday lives of athletes in professional and college sports, the crew comically highlights exclusive footage of the superstars spotted around Hollywood, New York Cit",
          "categories": [
            "News"
          ],
          "sportType": null,
          "competition": null,
          "imageUrl": null,
          "startAt": "2026-05-09T08:00:00Z",
          "endAt": "2026-05-09T08:30:00Z"
        },
        {
          "title": "TMZ Sports Weekend",
          "subtitle": null,
          "description": "The biggest sports stories and rumors of the week are covered, as the analysts break down the news surrounding each of the headlines to discuss how those involved will be impacted, along with guest in",
          "categories": [],
          "sportType": null,
          "competition": null,
          "imageUrl": null,
          "startAt": "2026-05-09T08:30:00Z",
          "endAt": "2026-05-09T09:00:00Z"
        },
        {
          "title": "ARCA Racing",
          "subtitle": null,
          "description": "from Watkins Glen International in Watkins Glen, N.Y.",
          "categories": [],
          "sportType": null,
          "competition": null,
          "imageUrl": null,
          "startAt": "2026-05-09T09:00:00Z",
          "endAt": "2026-05-09T11:00:00Z"
        },
        {
          "title": "GT4 America",
          "subtitle": null,
          "description": "from Circuit of the Americas, Austin, Texas",
          "categories": [],
          "sportType": null,
          "competition": null,
          "imageUrl": null,
          "startAt": "2026-05-09T11:00:00Z",
          "endAt": "2026-05-09T12:00:00Z"
        },
        {
          "title": "Bassmaster Elite Series",
          "subtitle": null,
          "description": "The highest level of professional bass fishing features pro anglers competing all season for the opportunity to win points toward the Progressive Bassmaster Angler of the Year award and to qualify for",
          "categories": [],
          "sportType": null,
          "competition": null,
          "imageUrl": null,
          "startAt": "2026-05-09T12:00:00Z",
          "endAt": "2026-05-09T15:30:00Z"
        },
        {
          "title": "Indycar NICS Warmup",
          "subtitle": null,
          "description": "from Indianapolis Motor Speedway Road Course",
          "categories": [],
          "sportType": "Motorsport",
          "competition": null,
          "imageUrl": null,
          "startAt": "2026-05-09T15:30:00Z",
          "endAt": "2026-05-09T16:30:00Z"
        },
        {
          "title": "America's Day at the Races",
          "subtitle": null,
          "description": "Nationwide coverage of thoroughbred racing from venues around the country, showcasing major stakes races with in-depth analysis from expert handicappers; coverage includes the latest horse racing news",
          "categories": [],
          "sportType": null,
          "competition": null,
          "imageUrl": null,
          "startAt": "2026-05-09T16:30:00Z",
          "endAt": "2026-05-09T18:30:00Z"
        },
        {
          "title": "Indycar INXT Racing",
          "subtitle": null,
          "description": "from Indianapolis Motor Speedway Road Course",
          "categories": [],
          "sportType": "Motorsport",
          "competition": null,
          "imageUrl": null,
          "startAt": "2026-05-09T18:30:00Z",
          "endAt": "2026-05-09T19:30:00Z"
        },
        {
          "title": "MLB on FS1 Pregame",
          "subtitle": null,
          "description": "Expert analysts preview the upcoming MLB games, looking at the pitching matchups, evaluating key players on each team and assessing which players might have the biggest impact; coverage includes inter",
          "categories": [],
          "sportType": "Baseball",
          "competition": "MLB",
          "imageUrl": null,
          "startAt": "2026-05-09T19:30:00Z",
          "endAt": "2026-05-09T20:00:00Z"
        },
        {
          "title": "MLB Baseball",
          "subtitle": null,
          "description": "Houston Astros at Cincinnati Reds from Great American Ball Park",
          "categories": [],
          "sportType": "Baseball",
          "competition": "MLB",
          "imageUrl": null,
          "startAt": "2026-05-09T20:00:00Z",
          "endAt": "2026-05-09T23:00:00Z"
        }
      ]
    },
    {
      "id": "FoxSports2.us",
      "name": "FOX Sports 2",
      "logoUrl": "https://i.imgur.com/LHtxKI8.png",
      "provider": "TV Guide US sports guide",
      "providerKey": "premium-tvguide-us",
      "sources": [
        "data/normalized/guide-premium-US-tvguide.com.xml"
      ],
      "currentProgram": {
        "title": "Fox Sports FIFA World Cup Rank",
        "subtitle": null,
        "description": null,
        "categories": [],
        "sportType": null,
        "competition": null,
        "imageUrl": null,
        "startAt": "2026-05-09T02:00:00Z",
        "endAt": "2026-05-09T02:30:00Z"
      },
      "programs": [
        {
          "title": "Indycar NICS Qualifications",
          "subtitle": null,
          "description": "from Indianapolis Motor Speedway Road Course",
          "categories": [],
          "sportType": "Motorsport",
          "competition": null,
          "imageUrl": null,
          "startAt": "2026-05-08T21:30:00Z",
          "endAt": "2026-05-08T23:00:00Z"
        },
        {
          "title": "Football Nation",
          "subtitle": null,
          "description": null,
          "categories": [],
          "sportType": "Football",
          "competition": null,
          "imageUrl": null,
          "startAt": "2026-05-08T23:00:00Z",
          "endAt": "2026-05-08T23:30:00Z"
        },
        {
          "title": "Football Nation",
          "subtitle": null,
          "description": null,
          "categories": [],
          "sportType": "Football",
          "competition": null,
          "imageUrl": null,
          "startAt": "2026-05-08T23:30:00Z",
          "endAt": "2026-05-09T00:00:00Z"
        },
        {
          "title": "Pickleball",
          "subtitle": null,
          "description": "The James has been named the official and exclusive hospital of the upcoming 2024 APP Vlasic Classic in Cincinnati on May 7-12.",
          "categories": [],
          "sportType": null,
          "competition": null,
          "imageUrl": null,
          "startAt": "2026-05-09T00:00:00Z",
          "endAt": "2026-05-09T02:00:00Z"
        },
        {
          "title": "Fox Sports FIFA World Cup Rank",
          "subtitle": null,
          "description": null,
          "categories": [],
          "sportType": null,
          "competition": null,
          "imageUrl": null,
          "startAt": "2026-05-09T02:00:00Z",
          "endAt": "2026-05-09T02:30:00Z"
        },
        {
          "title": "LIV Golf",
          "subtitle": null,
          "description": "from Trump National Golf Club Washington, D.C.",
          "categories": [],
          "sportType": "Golf",
          "competition": null,
          "imageUrl": null,
          "startAt": "2026-05-09T02:30:00Z",
          "endAt": "2026-05-09T05:30:00Z"
        },
        {
          "title": "Indycar NICS Qualifications",
          "subtitle": null,
          "description": "from Indianapolis Motor Speedway Road Course",
          "categories": [],
          "sportType": "Motorsport",
          "competition": null,
          "imageUrl": null,
          "startAt": "2026-05-09T05:30:00Z",
          "endAt": "2026-05-09T07:00:00Z"
        },
        {
          "title": "NASCAR Craftsman Truck Series",
          "subtitle": null,
          "description": "from Watkins Glen International in Watkins Glen, N.Y.",
          "categories": [],
          "sportType": "Motorsport",
          "competition": null,
          "imageUrl": null,
          "startAt": "2026-05-09T07:00:00Z",
          "endAt": "2026-05-09T09:00:00Z"
        },
        {
          "title": "FIFA World Cup 26: Preview Series",
          "subtitle": null,
          "description": null,
          "categories": [],
          "sportType": null,
          "competition": null,
          "imageUrl": null,
          "startAt": "2026-05-09T09:00:00Z",
          "endAt": "2026-05-09T09:30:00Z"
        },
        {
          "title": "Australian Football League",
          "subtitle": null,
          "description": "Geelong Cats at Collingwood Magpies from The MCG",
          "categories": [],
          "sportType": "Football",
          "competition": null,
          "imageUrl": null,
          "startAt": "2026-05-09T09:30:00Z",
          "endAt": "2026-05-09T12:30:00Z"
        },
        {
          "title": "MotoGP: Fabio Quartararo: The Road To Redemption",
          "subtitle": null,
          "description": null,
          "categories": [],
          "sportType": null,
          "competition": null,
          "imageUrl": null,
          "startAt": "2026-05-09T12:30:00Z",
          "endAt": "2026-05-09T12:55:00Z"
        },
        {
          "title": "MotoGP",
          "subtitle": "France Grand Prix Sprint Race",
          "description": "from Bugatti Circuit in Le Mans, France",
          "categories": [
            "Sports"
          ],
          "sportType": "Sports",
          "competition": null,
          "imageUrl": null,
          "startAt": "2026-05-09T12:55:00Z",
          "endAt": "2026-05-09T13:30:00Z"
        },
        {
          "title": "UFL Football",
          "subtitle": null,
          "description": "Columbus Aviators at St. Louis Battlehawks from The Dome at America's Center",
          "categories": [],
          "sportType": "Football",
          "competition": null,
          "imageUrl": null,
          "startAt": "2026-05-09T13:30:00Z",
          "endAt": "2026-05-09T16:30:00Z"
        },
        {
          "title": "NHRA Sportsman Series",
          "subtitle": null,
          "description": "The top drag racing teams in the country compete in different classifications; drivers accumulate points based on the results of each event and at the end of the season a champion is crowned in the va",
          "categories": [],
          "sportType": null,
          "competition": null,
          "imageUrl": null,
          "startAt": "2026-05-09T16:30:00Z",
          "endAt": "2026-05-09T17:30:00Z"
        },
        {
          "title": "GT World Challenge America",
          "subtitle": null,
          "description": "Started in 1990, drivers compete in five different classes of vehicles across the United States and Canada, taking on varying courses and street circuits as the drivers look to take the checkered flag",
          "categories": [],
          "sportType": null,
          "competition": null,
          "imageUrl": null,
          "startAt": "2026-05-09T17:30:00Z",
          "endAt": "2026-05-09T18:30:00Z"
        },
        {
          "title": "America's Day at the Races",
          "subtitle": null,
          "description": "Nationwide coverage of thoroughbred racing from venues around the country, showcasing major stakes races with in-depth analysis from expert handicappers; coverage includes the latest horse racing news",
          "categories": [],
          "sportType": null,
          "competition": null,
          "imageUrl": null,
          "startAt": "2026-05-09T18:30:00Z",
          "endAt": "2026-05-09T22:30:00Z"
        }
      ]
    },
    {
      "id": "ESPN.us",
      "name": "ESPN",
      "logoUrl": "https://upload.wikimedia.org/wikipedia/commons/thumb/2/2f/ESPN_wordmark.svg/960px-ESPN_wordmark.svg.png",
      "provider": "TVTV US sports guide",
      "providerKey": "premium-tvtv-us",
      "sources": [
        "data/normalized/guide-premium-US-tvtv.us.xml",
        "data/normalized/guide-premium-US-tvguide.com.xml"
      ],
      "currentProgram": {
        "title": "SportsCenter",
        "subtitle": null,
        "description": "The worldwide leader in sports covers all the important stories of the day, including game highlights, player interviews, and special segments; correspondents relay up-to-the-minute news and game-day",
        "categories": [
          "News",
          "Sports",
          "Talk & Interview"
        ],
        "sportType": "Sports",
        "competition": null,
        "imageUrl": null,
        "startAt": "2026-05-09T01:30:00Z",
        "endAt": "2026-05-09T03:00:00Z"
      },
      "programs": [
        {
          "title": "College Softball",
          "subtitle": null,
          "description": "from John Cropp Stadium in Lexington, Ky.",
          "categories": [],
          "sportType": null,
          "competition": null,
          "imageUrl": null,
          "startAt": "2026-05-08T21:00:00Z",
          "endAt": "2026-05-08T23:00:00Z"
        },
        {
          "title": "SEC Now",
          "subtitle": null,
          "description": "Hosts and analysts break down the latest sports news around the SEC, taking a comprehensive look at how it impacts their team moving forward, along with in-depth features on players, coaches and teams",
          "categories": [],
          "sportType": null,
          "competition": null,
          "imageUrl": null,
          "startAt": "2026-05-08T23:00:00Z",
          "endAt": "2026-05-08T23:30:00Z"
        },
        {
          "title": "College Softball",
          "subtitle": null,
          "description": "from John Cropp Stadium in Lexington, Ky.",
          "categories": [],
          "sportType": null,
          "competition": null,
          "imageUrl": null,
          "startAt": "2026-05-08T23:30:00Z",
          "endAt": "2026-05-09T01:30:00Z"
        },
        {
          "title": "SportsCenter",
          "subtitle": null,
          "description": "The worldwide leader in sports covers all the important stories of the day, including game highlights, player interviews, and special segments; correspondents relay up-to-the-minute news and game-day",
          "categories": [
            "News",
            "Sports",
            "Talk & Interview"
          ],
          "sportType": "Sports",
          "competition": null,
          "imageUrl": null,
          "startAt": "2026-05-09T01:30:00Z",
          "endAt": "2026-05-09T03:00:00Z"
        },
        {
          "title": "SportsCenter",
          "subtitle": null,
          "description": "The worldwide leader in sports covers all the important stories of the day, including game highlights, player interviews, and special segments; correspondents relay up-to-the-minute news and game-day",
          "categories": [
            "News",
            "Sports",
            "Talk & Interview"
          ],
          "sportType": "Sports",
          "competition": null,
          "imageUrl": null,
          "startAt": "2026-05-09T03:00:00Z",
          "endAt": "2026-05-09T04:00:00Z"
        },
        {
          "title": "SportsCenter",
          "subtitle": null,
          "description": "The worldwide leader in sports covers all the important stories of the day, including game highlights, player interviews, and special segments; correspondents relay up-to-the-minute news and game-day",
          "categories": [
            "News",
            "Sports",
            "Talk & Interview"
          ],
          "sportType": "Sports",
          "competition": null,
          "imageUrl": null,
          "startAt": "2026-05-09T04:00:00Z",
          "endAt": "2026-05-09T05:00:00Z"
        },
        {
          "title": "SportsCenter",
          "subtitle": null,
          "description": "The worldwide leader in sports covers all the important stories of the day, including game highlights, player interviews, and special segments; correspondents relay up-to-the-minute news and game-day",
          "categories": [
            "News",
            "Sports",
            "Talk & Interview"
          ],
          "sportType": "Sports",
          "competition": null,
          "imageUrl": null,
          "startAt": "2026-05-09T05:00:00Z",
          "endAt": "2026-05-09T06:00:00Z"
        },
        {
          "title": "SportsCenter",
          "subtitle": null,
          "description": "The worldwide leader in sports covers all the important stories of the day, including game highlights, player interviews, and special segments; correspondents relay up-to-the-minute news and game-day",
          "categories": [
            "News",
            "Sports",
            "Talk & Interview"
          ],
          "sportType": "Sports",
          "competition": null,
          "imageUrl": null,
          "startAt": "2026-05-09T06:00:00Z",
          "endAt": "2026-05-09T07:00:00Z"
        },
        {
          "title": "SportsCenter",
          "subtitle": null,
          "description": "The worldwide leader in sports covers all the important stories of the day, including game highlights, player interviews, and special segments; correspondents relay up-to-the-minute news and game-day",
          "categories": [
            "News",
            "Sports",
            "Talk & Interview"
          ],
          "sportType": "Sports",
          "competition": null,
          "imageUrl": null,
          "startAt": "2026-05-09T07:00:00Z",
          "endAt": "2026-05-09T08:00:00Z"
        },
        {
          "title": "SportsCenter",
          "subtitle": null,
          "description": "The worldwide leader in sports covers all the important stories of the day, including game highlights, player interviews, and special segments; correspondents relay up-to-the-minute news and game-day",
          "categories": [
            "News",
            "Sports",
            "Talk & Interview"
          ],
          "sportType": "Sports",
          "competition": null,
          "imageUrl": null,
          "startAt": "2026-05-09T08:00:00Z",
          "endAt": "2026-05-09T09:00:00Z"
        },
        {
          "title": "SportsCenter",
          "subtitle": null,
          "description": "The worldwide leader in sports covers all the important stories of the day, including game highlights, player interviews, and special segments; correspondents relay up-to-the-minute news and game-day",
          "categories": [
            "News",
            "Sports",
            "Talk & Interview"
          ],
          "sportType": "Sports",
          "competition": null,
          "imageUrl": null,
          "startAt": "2026-05-09T09:00:00Z",
          "endAt": "2026-05-09T10:00:00Z"
        },
        {
          "title": "SportsCenter",
          "subtitle": null,
          "description": "The worldwide leader in sports covers all the important stories of the day, including game highlights, player interviews, and special segments; correspondents relay up-to-the-minute news and game-day",
          "categories": [
            "News",
            "Sports",
            "Talk & Interview"
          ],
          "sportType": "Sports",
          "competition": null,
          "imageUrl": null,
          "startAt": "2026-05-09T10:00:00Z",
          "endAt": "2026-05-09T11:00:00Z"
        },
        {
          "title": "SportsCenter",
          "subtitle": null,
          "description": "The worldwide leader in sports covers all the important stories of the day, including game highlights, player interviews, and special segments; correspondents relay up-to-the-minute news and game-day",
          "categories": [
            "News",
            "Sports",
            "Talk & Interview"
          ],
          "sportType": "Sports",
          "competition": null,
          "imageUrl": null,
          "startAt": "2026-05-09T11:00:00Z",
          "endAt": "2026-05-09T12:00:00Z"
        },
        {
          "title": "SportsCenter",
          "subtitle": null,
          "description": "The worldwide leader in sports covers all the important stories of the day, including game highlights, player interviews, and special segments; correspondents relay up-to-the-minute news and game-day",
          "categories": [
            "News",
            "Sports",
            "Talk & Interview"
          ],
          "sportType": "Sports",
          "competition": null,
          "imageUrl": null,
          "startAt": "2026-05-09T12:00:00Z",
          "endAt": "2026-05-09T13:00:00Z"
        },
        {
          "title": "SportsCenter",
          "subtitle": null,
          "description": "The worldwide leader in sports covers all the important stories of the day, including game highlights, player interviews, and special segments; correspondents relay up-to-the-minute news and game-day",
          "categories": [
            "News",
            "Sports",
            "Talk & Interview"
          ],
          "sportType": "Sports",
          "competition": null,
          "imageUrl": null,
          "startAt": "2026-05-09T13:00:00Z",
          "endAt": "2026-05-09T14:00:00Z"
        },
        {
          "title": "SportsCenter",
          "subtitle": null,
          "description": "The worldwide leader in sports covers all the important stories of the day, including game highlights, player interviews, and special segments; correspondents relay up-to-the-minute news and game-day",
          "categories": [
            "News",
            "Sports",
            "Talk & Interview"
          ],
          "sportType": "Sports",
          "competition": null,
          "imageUrl": null,
          "startAt": "2026-05-09T14:00:00Z",
          "endAt": "2026-05-09T15:00:00Z"
        },
        {
          "title": "SportsCenter",
          "subtitle": null,
          "description": "The worldwide leader in sports covers all the important stories of the day, including game highlights, player interviews, and special segments; correspondents relay up-to-the-minute news and game-day",
          "categories": [
            "News",
            "Sports",
            "Talk & Interview"
          ],
          "sportType": "Sports",
          "competition": null,
          "imageUrl": null,
          "startAt": "2026-05-09T15:00:00Z",
          "endAt": "2026-05-09T16:00:00Z"
        },
        {
          "title": "College Softball",
          "subtitle": null,
          "description": "from Devon Park in Oklahoma City",
          "categories": [],
          "sportType": null,
          "competition": null,
          "imageUrl": null,
          "startAt": "2026-05-09T16:00:00Z",
          "endAt": "2026-05-09T18:30:00Z"
        },
        {
          "title": "College Softball",
          "subtitle": null,
          "description": "from UVA Palmer Park in Charlottesville, Va.",
          "categories": [],
          "sportType": null,
          "competition": null,
          "imageUrl": null,
          "startAt": "2026-05-09T18:30:00Z",
          "endAt": "2026-05-09T21:00:00Z"
        },
        {
          "title": "College Softball",
          "subtitle": null,
          "description": "from John Cropp Stadium in Lexington, Ky.",
          "categories": [],
          "sportType": null,
          "competition": null,
          "imageUrl": null,
          "startAt": "2026-05-09T21:00:00Z",
          "endAt": "2026-05-09T23:30:00Z"
        }
      ]
    },
    {
      "id": "ESPN2.us",
      "name": "ESPN 2",
      "logoUrl": "https://i.imgur.com/00tsvjE.png",
      "provider": "TVTV US sports guide",
      "providerKey": "premium-tvtv-us",
      "sources": [
        "data/normalized/guide-premium-US-tvtv.us.xml",
        "data/normalized/guide-premium-US-tvguide.com.xml"
      ],
      "currentProgram": {
        "title": "College Baseball",
        "subtitle": null,
        "description": "Oklahoma State Cowboys at Arizona State Sun Devils from Phoenix Municipal Stadium",
        "categories": [],
        "sportType": "Baseball",
        "competition": null,
        "imageUrl": null,
        "startAt": "2026-05-09T01:00:00Z",
        "endAt": "2026-05-09T04:00:00Z"
      },
      "programs": [
        {
          "title": "SportsCenter",
          "subtitle": null,
          "description": "The worldwide leader in sports covers all the important stories of the day, including game highlights, player interviews, and special segments; correspondents relay up-to-the-minute news and game-day",
          "categories": [
            "News",
            "Sports",
            "Talk & Interview"
          ],
          "sportType": "Sports",
          "competition": null,
          "imageUrl": null,
          "startAt": "2026-05-08T22:00:00Z",
          "endAt": "2026-05-08T23:00:00Z"
        },
        {
          "title": "NFL2Night",
          "subtitle": null,
          "description": "The latest news and reports around the NFL are discussed in detail with a panel of expert analysts weighing in on the hottest issues, while veteran football reporters provide up-to-date information fr",
          "categories": [
            "News",
            "Sports"
          ],
          "sportType": "Football",
          "competition": null,
          "imageUrl": null,
          "startAt": "2026-05-08T23:00:00Z",
          "endAt": "2026-05-09T00:00:00Z"
        },
        {
          "title": "SEC Inside",
          "subtitle": null,
          "description": "An all-access look focuses on Mississippi State baseball and coach Brian O'Connor as the Bulldogs prepare for their next opponent, showing coaches put their players through practice, hear the advice t",
          "categories": [],
          "sportType": "Baseball",
          "competition": null,
          "imageUrl": null,
          "startAt": "2026-05-09T00:00:00Z",
          "endAt": "2026-05-09T00:30:00Z"
        },
        {
          "title": "SEC Inside",
          "subtitle": null,
          "description": "An all-access look focuses on Texas A&M baseball and coach Michael Earley as the Aggies prepare for their upcoming opponent, showing coaches put their players through practice and hear the advice they",
          "categories": [],
          "sportType": "Baseball",
          "competition": null,
          "imageUrl": null,
          "startAt": "2026-05-09T00:30:00Z",
          "endAt": "2026-05-09T01:00:00Z"
        },
        {
          "title": "College Baseball",
          "subtitle": null,
          "description": "Oklahoma State Cowboys at Arizona State Sun Devils from Phoenix Municipal Stadium",
          "categories": [],
          "sportType": "Baseball",
          "competition": null,
          "imageUrl": null,
          "startAt": "2026-05-09T01:00:00Z",
          "endAt": "2026-05-09T04:00:00Z"
        },
        {
          "title": "30 for 30",
          "subtitle": null,
          "description": "Stuart Scott redefined what it meant to be a sports anchor, taking SportsCenter to the next level with his unique style and sayings that would transcend time, as even a cancer diagnosis would not slow",
          "categories": [
            "Documentary",
            "Sports"
          ],
          "sportType": "Sports",
          "competition": null,
          "imageUrl": null,
          "startAt": "2026-05-09T04:00:00Z",
          "endAt": "2026-05-09T05:30:00Z"
        },
        {
          "title": "Pardon the Interruption",
          "subtitle": null,
          "description": "Tony Kornheiser and Michael Wilbon, longtime colleagues and friends, engage in verbal sparring during a fast-paced and wide-ranging discussion about current events in the world of sports; Kornheiser a",
          "categories": [
            "News",
            "Sports",
            "Talk & Interview"
          ],
          "sportType": "Sports",
          "competition": null,
          "imageUrl": null,
          "startAt": "2026-05-09T05:30:00Z",
          "endAt": "2026-05-09T06:00:00Z"
        },
        {
          "title": "The Last Dance",
          "subtitle": null,
          "description": "Michael Jordan would famously use even the smallest slight imaginable to motivate himself against an opponent, and when his NBA comeback in 1995 fell short in the playoffs, he worked harder than ever",
          "categories": [],
          "sportType": "Basketball",
          "competition": "NBA",
          "imageUrl": null,
          "startAt": "2026-05-09T06:00:00Z",
          "endAt": "2026-05-09T07:00:00Z"
        },
        {
          "title": "The Last Dance",
          "subtitle": null,
          "description": "In 1998, a year after the Chicago Bulls defeated Utah in the NBA Finals, their path to a sixth title only gets more challenging as it goes along, as a brutal seven-game series against the Indiana Pace",
          "categories": [],
          "sportType": "Basketball",
          "competition": "NBA",
          "imageUrl": null,
          "startAt": "2026-05-09T07:00:00Z",
          "endAt": "2026-05-09T08:00:00Z"
        },
        {
          "title": "The Last Dance",
          "subtitle": null,
          "description": "In June of 1998, Michael Jordan and the Chicago Bulls take on the Utah Jazz in an NBA Finals rematch that saw the Bulls win in six games in the 1997 Finals, looking for a sixth championship and a perf",
          "categories": [],
          "sportType": "Basketball",
          "competition": "NBA",
          "imageUrl": null,
          "startAt": "2026-05-09T08:00:00Z",
          "endAt": "2026-05-09T09:00:00Z"
        },
        {
          "title": "NFL2Night",
          "subtitle": null,
          "description": "The latest news and reports around the NFL are discussed in detail with a panel of expert analysts weighing in on the hottest issues, while veteran football reporters provide up-to-date information fr",
          "categories": [
            "News",
            "Sports"
          ],
          "sportType": "Football",
          "competition": null,
          "imageUrl": null,
          "startAt": "2026-05-09T09:00:00Z",
          "endAt": "2026-05-09T10:00:00Z"
        },
        {
          "title": "Flats Class",
          "subtitle": null,
          "description": "The show's hosts fish from boats in the shallows of the ocean and Gulf shores of the southern US while giving out tips on everything from equipment, lure and bait selection to the right boat and motor",
          "categories": [],
          "sportType": null,
          "competition": null,
          "imageUrl": null,
          "startAt": "2026-05-09T10:00:00Z",
          "endAt": "2026-05-09T10:30:00Z"
        },
        {
          "title": "George Poveromo's World of Saltwater Fishing",
          "subtitle": null,
          "description": "Host George Poveromo travels throughout North America and participates in fishing adventures with hopes of catching a variety of different species at popular locales, while discussing the tactics and",
          "categories": [],
          "sportType": null,
          "competition": null,
          "imageUrl": null,
          "startAt": "2026-05-09T10:30:00Z",
          "endAt": "2026-05-09T11:00:00Z"
        },
        {
          "title": "Seasons on the Fly",
          "subtitle": null,
          "description": "Greg Heister showcases some of his award-winning fly-fishing techniques as he travels the country with various esteemed guests in pursuit of trophy-caliber fish, going over the equipment and different",
          "categories": [],
          "sportType": null,
          "competition": null,
          "imageUrl": null,
          "startAt": "2026-05-09T11:00:00Z",
          "endAt": "2026-05-09T11:30:00Z"
        },
        {
          "title": "Motorhead Garage",
          "subtitle": null,
          "description": "Dave Dobson covers the latest from around the automotive world, featuring reviews on the newest products to hit the market, his techniques on how to repair different issues on a variety of vehicles an",
          "categories": [],
          "sportType": null,
          "competition": null,
          "imageUrl": null,
          "startAt": "2026-05-09T11:30:00Z",
          "endAt": "2026-05-09T12:00:00Z"
        },
        {
          "title": "ESPN Films",
          "subtitle": null,
          "description": "The most remarkable sports stories are featured, as storytellers break away from the traditional view of a sports film and showcasing stories of passion, triumph, loss and resurgence of athletes, as f",
          "categories": [
            "Documentary"
          ],
          "sportType": null,
          "competition": null,
          "imageUrl": null,
          "startAt": "2026-05-09T12:00:00Z",
          "endAt": "2026-05-09T13:30:00Z"
        },
        {
          "title": "Game On",
          "subtitle": null,
          "description": null,
          "categories": [],
          "sportType": null,
          "competition": null,
          "imageUrl": null,
          "startAt": "2026-05-09T13:30:00Z",
          "endAt": "2026-05-09T14:30:00Z"
        },
        {
          "title": "NFL Films",
          "subtitle": null,
          "description": "The National Football League presents a closer, documentary-style look at the teams and towns featured prominently each week in the league, as well as a look at the most enigmatic personalities of the",
          "categories": [],
          "sportType": "Football",
          "competition": null,
          "imageUrl": null,
          "startAt": "2026-05-09T14:30:00Z",
          "endAt": "2026-05-09T16:00:00Z"
        },
        {
          "title": "College Softball",
          "subtitle": null,
          "description": "from Max R. Joyner Family Stadium in Greenville, S.C.",
          "categories": [],
          "sportType": null,
          "competition": null,
          "imageUrl": null,
          "startAt": "2026-05-09T16:00:00Z",
          "endAt": "2026-05-09T18:30:00Z"
        },
        {
          "title": "College Softball",
          "subtitle": null,
          "description": "from Lamson Park in Lafayette, La.",
          "categories": [],
          "sportType": null,
          "competition": null,
          "imageUrl": null,
          "startAt": "2026-05-09T18:30:00Z",
          "endAt": "2026-05-09T21:00:00Z"
        },
        {
          "title": "WWE",
          "subtitle": null,
          "description": "Analysts preview the WWE Backlash card and the title matches that highlight it, including Roman Reigns defending his World Heavyweight Championship against Jacob Fatu and Trick Williams defending his",
          "categories": [],
          "sportType": null,
          "competition": null,
          "imageUrl": null,
          "startAt": "2026-05-09T21:00:00Z",
          "endAt": "2026-05-09T22:00:00Z"
        },
        {
          "title": "WWE",
          "subtitle": null,
          "description": "from Benchmark International Arena in Tampa, Fla.",
          "categories": [],
          "sportType": null,
          "competition": null,
          "imageUrl": null,
          "startAt": "2026-05-09T22:00:00Z",
          "endAt": "2026-05-09T23:00:00Z"
        }
      ]
    },
    {
      "id": "ESPNews.us",
      "name": "ESPNEWS",
      "logoUrl": "https://upload.wikimedia.org/wikipedia/commons/thumb/1/1b/ESPNews.svg/960px-ESPNews.svg.png",
      "provider": "TVTV US sports guide",
      "providerKey": "premium-tvtv-us",
      "sources": [
        "data/normalized/guide-premium-US-tvtv.us.xml",
        "data/normalized/guide-premium-US-tvguide.com.xml"
      ],
      "currentProgram": {
        "title": "Chiney Today",
        "subtitle": null,
        "description": "Former WNBA player Chiney Ogwumike covers the latest from across the basketball world, breaking down the news making headlines, recaps of some of the recent marquee matchups and interviews with esteem",
        "categories": [],
        "sportType": "Basketball",
        "competition": null,
        "imageUrl": null,
        "startAt": "2026-05-09T02:00:00Z",
        "endAt": "2026-05-09T02:30:00Z"
      },
      "programs": [
        {
          "title": "Chiney Today",
          "subtitle": null,
          "description": "Former WNBA player Chiney Ogwumike covers the latest from across the basketball world, breaking down the news making headlines, recaps of some of the recent marquee matchups and interviews with esteem",
          "categories": [],
          "sportType": "Basketball",
          "competition": null,
          "imageUrl": null,
          "startAt": "2026-05-08T22:00:00Z",
          "endAt": "2026-05-08T22:30:00Z"
        },
        {
          "title": "Pardon the Interruption",
          "subtitle": null,
          "description": "Tony Kornheiser and Michael Wilbon, longtime colleagues and friends, engage in verbal sparring during a fast-paced and wide-ranging discussion about current events in the world of sports; Kornheiser a",
          "categories": [
            "News",
            "Sports",
            "Talk & Interview"
          ],
          "sportType": "Sports",
          "competition": null,
          "imageUrl": null,
          "startAt": "2026-05-08T22:30:00Z",
          "endAt": "2026-05-08T23:00:00Z"
        },
        {
          "title": "The Schrager Hour",
          "subtitle": null,
          "description": "Peter Schrager covers the latest surrounding the NFL, breaking down the latest news making headlines, insightful segments on various topics and interviews with players, coaches and front office member",
          "categories": [],
          "sportType": null,
          "competition": null,
          "imageUrl": null,
          "startAt": "2026-05-08T23:00:00Z",
          "endAt": "2026-05-09T00:00:00Z"
        },
        {
          "title": "Chiney Today",
          "subtitle": null,
          "description": "Former WNBA player Chiney Ogwumike covers the latest from across the basketball world, breaking down the news making headlines, recaps of some of the recent marquee matchups and interviews with esteem",
          "categories": [],
          "sportType": "Basketball",
          "competition": null,
          "imageUrl": null,
          "startAt": "2026-05-09T00:00:00Z",
          "endAt": "2026-05-09T00:30:00Z"
        },
        {
          "title": "Pardon the Interruption",
          "subtitle": null,
          "description": "Tony Kornheiser and Michael Wilbon, longtime colleagues and friends, engage in verbal sparring during a fast-paced and wide-ranging discussion about current events in the world of sports; Kornheiser a",
          "categories": [
            "News",
            "Sports",
            "Talk & Interview"
          ],
          "sportType": "Sports",
          "competition": null,
          "imageUrl": null,
          "startAt": "2026-05-09T00:30:00Z",
          "endAt": "2026-05-09T01:00:00Z"
        },
        {
          "title": "The Schrager Hour",
          "subtitle": null,
          "description": "Peter Schrager covers the latest surrounding the NFL, breaking down the latest news making headlines, insightful segments on various topics and interviews with players, coaches and front office member",
          "categories": [],
          "sportType": null,
          "competition": null,
          "imageUrl": null,
          "startAt": "2026-05-09T01:00:00Z",
          "endAt": "2026-05-09T02:00:00Z"
        },
        {
          "title": "Chiney Today",
          "subtitle": null,
          "description": "Former WNBA player Chiney Ogwumike covers the latest from across the basketball world, breaking down the news making headlines, recaps of some of the recent marquee matchups and interviews with esteem",
          "categories": [],
          "sportType": "Basketball",
          "competition": null,
          "imageUrl": null,
          "startAt": "2026-05-09T02:00:00Z",
          "endAt": "2026-05-09T02:30:00Z"
        },
        {
          "title": "Pardon the Interruption",
          "subtitle": null,
          "description": "Tony Kornheiser and Michael Wilbon, longtime colleagues and friends, engage in verbal sparring during a fast-paced and wide-ranging discussion about current events in the world of sports; Kornheiser a",
          "categories": [
            "News",
            "Sports",
            "Talk & Interview"
          ],
          "sportType": "Sports",
          "competition": null,
          "imageUrl": null,
          "startAt": "2026-05-09T02:30:00Z",
          "endAt": "2026-05-09T03:00:00Z"
        },
        {
          "title": "Chiney Today",
          "subtitle": null,
          "description": "Former WNBA player Chiney Ogwumike covers the latest from across the basketball world, breaking down the news making headlines, recaps of some of the recent marquee matchups and interviews with esteem",
          "categories": [],
          "sportType": "Basketball",
          "competition": null,
          "imageUrl": null,
          "startAt": "2026-05-09T03:00:00Z",
          "endAt": "2026-05-09T03:30:00Z"
        },
        {
          "title": "Pardon the Interruption",
          "subtitle": null,
          "description": "Tony Kornheiser and Michael Wilbon, longtime colleagues and friends, engage in verbal sparring during a fast-paced and wide-ranging discussion about current events in the world of sports; Kornheiser a",
          "categories": [
            "News",
            "Sports",
            "Talk & Interview"
          ],
          "sportType": "Sports",
          "competition": null,
          "imageUrl": null,
          "startAt": "2026-05-09T03:30:00Z",
          "endAt": "2026-05-09T04:00:00Z"
        },
        {
          "title": "Monster Energy's Rip to Cabo 2026",
          "subtitle": null,
          "description": null,
          "categories": [],
          "sportType": null,
          "competition": null,
          "imageUrl": null,
          "startAt": "2026-05-09T04:00:00Z",
          "endAt": "2026-05-09T05:00:00Z"
        },
        {
          "title": "X Games Ventura 2024",
          "subtitle": null,
          "description": "The world's best men's and women's action sports stars head to California to compete in the annual summer showcase, featuring skateboard, BMX, and Moto X events across three days with medals handed ou",
          "categories": [],
          "sportType": null,
          "competition": null,
          "imageUrl": null,
          "startAt": "2026-05-09T05:00:00Z",
          "endAt": "2026-05-09T06:00:00Z"
        },
        {
          "title": "Chiney Today",
          "subtitle": null,
          "description": "Former WNBA player Chiney Ogwumike covers the latest from across the basketball world, breaking down the news making headlines, recaps of some of the recent marquee matchups and interviews with esteem",
          "categories": [],
          "sportType": "Basketball",
          "competition": null,
          "imageUrl": null,
          "startAt": "2026-05-09T06:00:00Z",
          "endAt": "2026-05-09T06:30:00Z"
        },
        {
          "title": "Pardon the Interruption",
          "subtitle": null,
          "description": "Tony Kornheiser and Michael Wilbon, longtime colleagues and friends, engage in verbal sparring during a fast-paced and wide-ranging discussion about current events in the world of sports; Kornheiser a",
          "categories": [
            "News",
            "Sports",
            "Talk & Interview"
          ],
          "sportType": "Sports",
          "competition": null,
          "imageUrl": null,
          "startAt": "2026-05-09T06:30:00Z",
          "endAt": "2026-05-09T07:00:00Z"
        },
        {
          "title": "2019 World Sign Spinning Championship",
          "subtitle": null,
          "description": "The 12th annual world championship brings together the top AArrow Sign Spinners from 50 cities and 12 countries to compete, showcasing their sign routines as they are judged on style, execution, and t",
          "categories": [],
          "sportType": null,
          "competition": null,
          "imageUrl": null,
          "startAt": "2026-05-09T07:00:00Z",
          "endAt": "2026-05-09T07:30:00Z"
        },
        {
          "title": "Crossnet Sand Series: SoCal",
          "subtitle": null,
          "description": "A newer sport that presents elements of four square and volleyball, eliminating players as the game goes along; the first player to secure eleven points wins.",
          "categories": [],
          "sportType": null,
          "competition": null,
          "imageUrl": null,
          "startAt": "2026-05-09T07:30:00Z",
          "endAt": "2026-05-09T08:00:00Z"
        },
        {
          "title": "Franklin Rock River Stone Skipping Tournament",
          "subtitle": null,
          "description": "from Riverfront Park in Franklin, Pa.",
          "categories": [],
          "sportType": null,
          "competition": null,
          "imageUrl": null,
          "startAt": "2026-05-09T08:00:00Z",
          "endAt": "2026-05-09T08:30:00Z"
        },
        {
          "title": "2022 Noblesville Bed Races",
          "subtitle": null,
          "description": null,
          "categories": [],
          "sportType": null,
          "competition": null,
          "imageUrl": null,
          "startAt": "2026-05-09T08:30:00Z",
          "endAt": "2026-05-09T09:00:00Z"
        },
        {
          "title": "Chiney Today",
          "subtitle": null,
          "description": "Former WNBA player Chiney Ogwumike covers the latest from across the basketball world, breaking down the news making headlines, recaps of some of the recent marquee matchups and interviews with esteem",
          "categories": [],
          "sportType": "Basketball",
          "competition": null,
          "imageUrl": null,
          "startAt": "2026-05-09T09:00:00Z",
          "endAt": "2026-05-09T09:30:00Z"
        },
        {
          "title": "Pardon the Interruption",
          "subtitle": null,
          "description": "Tony Kornheiser and Michael Wilbon, longtime colleagues and friends, engage in verbal sparring during a fast-paced and wide-ranging discussion about current events in the world of sports; Kornheiser a",
          "categories": [
            "News",
            "Sports",
            "Talk & Interview"
          ],
          "sportType": "Sports",
          "competition": null,
          "imageUrl": null,
          "startAt": "2026-05-09T09:30:00Z",
          "endAt": "2026-05-09T10:00:00Z"
        },
        {
          "title": "IWL Wrestball 3x3",
          "subtitle": null,
          "description": null,
          "categories": [],
          "sportType": null,
          "competition": null,
          "imageUrl": null,
          "startAt": "2026-05-09T10:00:00Z",
          "endAt": "2026-05-09T11:00:00Z"
        },
        {
          "title": "Major League Paintball",
          "subtitle": null,
          "description": "from Walt Disney World Resort in Orlando, Fla.",
          "categories": [],
          "sportType": null,
          "competition": null,
          "imageUrl": null,
          "startAt": "2026-05-09T11:00:00Z",
          "endAt": "2026-05-09T12:00:00Z"
        },
        {
          "title": "Great American Events",
          "subtitle": null,
          "description": null,
          "categories": [],
          "sportType": null,
          "competition": null,
          "imageUrl": null,
          "startAt": "2026-05-09T12:00:00Z",
          "endAt": "2026-05-09T13:00:00Z"
        },
        {
          "title": "Omegaball",
          "subtitle": null,
          "description": "The unique soccer features three teams of five on the field at the same time playing on a smaller, circular field, creating a hectic pace in having two goals to score on while potentially having two d",
          "categories": [],
          "sportType": "Football",
          "competition": null,
          "imageUrl": null,
          "startAt": "2026-05-09T13:00:00Z",
          "endAt": "2026-05-09T14:00:00Z"
        },
        {
          "title": "Bullshooter",
          "subtitle": null,
          "description": "The top darts players from across the United States compete in the soft-tip electronic darts tournament to crown a champion, who will take home a significant cash prize, as they take part in head-to-h",
          "categories": [],
          "sportType": null,
          "competition": null,
          "imageUrl": null,
          "startAt": "2026-05-09T14:00:00Z",
          "endAt": "2026-05-09T15:00:00Z"
        },
        {
          "title": "Slippery Stairs",
          "subtitle": null,
          "description": "Five men and women compete at the Orange County Fair in a unique competition that requires them to race up to the top of multiple flights of stairs while dealing with slippery obstacles that can possi",
          "categories": [],
          "sportType": null,
          "competition": null,
          "imageUrl": null,
          "startAt": "2026-05-09T15:00:00Z",
          "endAt": "2026-05-09T16:00:00Z"
        },
        {
          "title": "Archery",
          "subtitle": null,
          "description": "The unique sport combining archery and dodgeball pits teams of four players against each other as they look to hit each other with foam tipped arrows as they hide behind cover and other obstacles to s",
          "categories": [],
          "sportType": null,
          "competition": null,
          "imageUrl": null,
          "startAt": "2026-05-09T16:00:00Z",
          "endAt": "2026-05-09T17:00:00Z"
        },
        {
          "title": "Dodgeball",
          "subtitle": null,
          "description": "The NDL Amateur World Championships feature the top teams from all over the world competing in their respective divisions in search of the tournament title, as the teams take part in team vs. team mat",
          "categories": [],
          "sportType": null,
          "competition": null,
          "imageUrl": null,
          "startAt": "2026-05-09T17:00:00Z",
          "endAt": "2026-05-09T18:00:00Z"
        },
        {
          "title": "World Axe Throwing League",
          "subtitle": null,
          "description": "Started in 2017, the league features members from around the world competing in circuit events as they look to take home the title; throwers are awarded five points for a bullseye, and have eight-poin",
          "categories": [],
          "sportType": null,
          "competition": null,
          "imageUrl": null,
          "startAt": "2026-05-09T18:00:00Z",
          "endAt": "2026-05-09T19:00:00Z"
        },
        {
          "title": "2025 Blackbird Cup - Alberta Pro Roller Hockey League",
          "subtitle": null,
          "description": null,
          "categories": [],
          "sportType": "Hockey",
          "competition": null,
          "imageUrl": null,
          "startAt": "2026-05-09T19:00:00Z",
          "endAt": "2026-05-09T20:00:00Z"
        },
        {
          "title": "National Ball Hockey League",
          "subtitle": null,
          "description": null,
          "categories": [],
          "sportType": "Hockey",
          "competition": null,
          "imageUrl": null,
          "startAt": "2026-05-09T20:00:00Z",
          "endAt": "2026-05-09T21:00:00Z"
        },
        {
          "title": "Jai Alai",
          "subtitle": null,
          "description": "Dubbed the \"world's fastest game\", Jai-Alai involves bouncing a ball off a walled-in space by accelerating it to high speeds with a cesta, a long, curved hand-held device, in head-to-head matchups of",
          "categories": [],
          "sportType": null,
          "competition": null,
          "imageUrl": null,
          "startAt": "2026-05-09T21:00:00Z",
          "endAt": "2026-05-09T22:00:00Z"
        },
        {
          "title": "Great American Events",
          "subtitle": null,
          "description": null,
          "categories": [],
          "sportType": null,
          "competition": null,
          "imageUrl": null,
          "startAt": "2026-05-09T22:00:00Z",
          "endAt": "2026-05-09T22:30:00Z"
        }
      ]
    },
    {
      "id": "ESPNU.us",
      "name": "ESPNU",
      "logoUrl": "https://i.imgur.com/HiBrysh.png",
      "provider": "TVTV US sports guide",
      "providerKey": "premium-tvtv-us",
      "sources": [
        "data/normalized/guide-premium-US-tvtv.us.xml",
        "data/normalized/guide-premium-US-tvguide.com.xml"
      ],
      "currentProgram": {
        "title": "College Softball",
        "subtitle": null,
        "description": "Saint Mary's (Calif.) Gaels at Santa Clara Broncos from SCU Softball Field",
        "categories": [],
        "sportType": null,
        "competition": null,
        "imageUrl": null,
        "startAt": "2026-05-09T02:00:00Z",
        "endAt": "2026-05-09T04:00:00Z"
      },
      "programs": [
        {
          "title": "ACCN Documentary",
          "subtitle": null,
          "description": null,
          "categories": [],
          "sportType": null,
          "competition": null,
          "imageUrl": null,
          "startAt": "2026-05-08T22:00:00Z",
          "endAt": "2026-05-08T23:00:00Z"
        },
        {
          "title": "College Baseball",
          "subtitle": null,
          "description": "Illinois State Redbirds at Illinois-Chicago Flames from Granderson Stadium",
          "categories": [],
          "sportType": "Baseball",
          "competition": null,
          "imageUrl": null,
          "startAt": "2026-05-08T23:00:00Z",
          "endAt": "2026-05-09T02:00:00Z"
        },
        {
          "title": "College Softball",
          "subtitle": null,
          "description": "Saint Mary's (Calif.) Gaels at Santa Clara Broncos from SCU Softball Field",
          "categories": [],
          "sportType": null,
          "competition": null,
          "imageUrl": null,
          "startAt": "2026-05-09T02:00:00Z",
          "endAt": "2026-05-09T04:00:00Z"
        },
        {
          "title": "SEC Inside",
          "subtitle": null,
          "description": "An all-access look focuses on South Carolina softball and coach Ashley Chastain as the Gamecocks prepare for their upcoming opponent, showing coaches put their players through practice and hear the ad",
          "categories": [],
          "sportType": null,
          "competition": null,
          "imageUrl": null,
          "startAt": "2026-05-09T04:00:00Z",
          "endAt": "2026-05-09T04:30:00Z"
        },
        {
          "title": "SEC Inside",
          "subtitle": null,
          "description": "An all-access look focuses on Ole Miss baseball and coach Mike Bianco as the Rebels prepare for their upcoming opponent, showing coaches put their players through practice and hear the advice they giv",
          "categories": [],
          "sportType": "Baseball",
          "competition": null,
          "imageUrl": null,
          "startAt": "2026-05-09T04:30:00Z",
          "endAt": "2026-05-09T05:00:00Z"
        },
        {
          "title": "SEC Inside",
          "subtitle": null,
          "description": "SEC teams prepare for their upcoming opponent with practice sessions and work inside the film room, featuring coaches drilling their players and offering advice, an exclusive look at how the schools g",
          "categories": [],
          "sportType": null,
          "competition": null,
          "imageUrl": null,
          "startAt": "2026-05-09T05:00:00Z",
          "endAt": "2026-05-09T05:30:00Z"
        },
        {
          "title": "SEC Inside",
          "subtitle": null,
          "description": "An all-access look focuses on Mississippi State baseball and coach Brian O'Connor as the Bulldogs prepare for their next opponent, showing coaches put their players through practice, hear the advice t",
          "categories": [],
          "sportType": "Baseball",
          "competition": null,
          "imageUrl": null,
          "startAt": "2026-05-09T05:30:00Z",
          "endAt": "2026-05-09T06:00:00Z"
        },
        {
          "title": "College Softball",
          "subtitle": null,
          "description": "from John Cropp Stadium in Lexington, Ky.",
          "categories": [],
          "sportType": null,
          "competition": null,
          "imageUrl": null,
          "startAt": "2026-05-09T06:00:00Z",
          "endAt": "2026-05-09T08:00:00Z"
        },
        {
          "title": "College Softball",
          "subtitle": null,
          "description": "from John Cropp Stadium in Lexington, Ky.",
          "categories": [],
          "sportType": null,
          "competition": null,
          "imageUrl": null,
          "startAt": "2026-05-09T08:00:00Z",
          "endAt": "2026-05-09T10:00:00Z"
        },
        {
          "title": "College Softball",
          "subtitle": null,
          "description": "Saint Mary's (Calif.) Gaels at Santa Clara Broncos from SCU Softball Field",
          "categories": [],
          "sportType": null,
          "competition": null,
          "imageUrl": null,
          "startAt": "2026-05-09T10:00:00Z",
          "endAt": "2026-05-09T12:00:00Z"
        },
        {
          "title": "The Climb: LSU Gymnastics",
          "subtitle": null,
          "description": "The docuseries follows the LSU gymnastics team as they go through their season, attempting to regain their dominance in the SEC and make a deep postseason run like in the 2010s, when the Tigers advanc",
          "categories": [],
          "sportType": null,
          "competition": null,
          "imageUrl": null,
          "startAt": "2026-05-09T12:00:00Z",
          "endAt": "2026-05-09T12:30:00Z"
        },
        {
          "title": "The Climb: LSU Gymnastics",
          "subtitle": null,
          "description": "The docuseries follows the LSU gymnastics team as they go through their season, attempting to regain their dominance in the SEC and make a deep postseason run like in the 2010s, when the Tigers advanc",
          "categories": [],
          "sportType": null,
          "competition": null,
          "imageUrl": null,
          "startAt": "2026-05-09T12:30:00Z",
          "endAt": "2026-05-09T13:00:00Z"
        },
        {
          "title": "The Climb: LSU Gymnastics",
          "subtitle": null,
          "description": "The docuseries follows the LSU gymnastics team as they go through their season, attempting to regain their dominance in the SEC and make a deep postseason run like in the 2010s, when the Tigers advanc",
          "categories": [],
          "sportType": null,
          "competition": null,
          "imageUrl": null,
          "startAt": "2026-05-09T13:00:00Z",
          "endAt": "2026-05-09T13:30:00Z"
        },
        {
          "title": "The Climb: LSU Gymnastics",
          "subtitle": null,
          "description": "The docuseries follows the LSU gymnastics team as they go through their season, attempting to regain their dominance in the SEC and make a deep postseason run like in the 2010s, when the Tigers advanc",
          "categories": [],
          "sportType": null,
          "competition": null,
          "imageUrl": null,
          "startAt": "2026-05-09T13:30:00Z",
          "endAt": "2026-05-09T14:00:00Z"
        },
        {
          "title": "The Climb: LSU Gymnastics",
          "subtitle": null,
          "description": "The docuseries follows the LSU gymnastics team as they go through their season, attempting to regain their dominance in the SEC and make a deep postseason run like in the 2010s, when the Tigers advanc",
          "categories": [],
          "sportType": null,
          "competition": null,
          "imageUrl": null,
          "startAt": "2026-05-09T14:00:00Z",
          "endAt": "2026-05-09T14:30:00Z"
        },
        {
          "title": "The Climb: LSU Gymnastics",
          "subtitle": null,
          "description": "The docuseries follows the LSU gymnastics team as they go through their season, attempting to regain their dominance in the SEC and make a deep postseason run like in the 2010s, when the Tigers advanc",
          "categories": [],
          "sportType": null,
          "competition": null,
          "imageUrl": null,
          "startAt": "2026-05-09T14:30:00Z",
          "endAt": "2026-05-09T15:00:00Z"
        },
        {
          "title": "The Climb: LSU Gymnastics",
          "subtitle": null,
          "description": "The docuseries follows the LSU gymnastics team as they go through their season, attempting to regain their dominance in the SEC and make a deep postseason run like in the 2010s, when the Tigers advanc",
          "categories": [],
          "sportType": null,
          "competition": null,
          "imageUrl": null,
          "startAt": "2026-05-09T15:00:00Z",
          "endAt": "2026-05-09T15:30:00Z"
        },
        {
          "title": "The Climb: LSU Gymnastics",
          "subtitle": null,
          "description": "The docuseries follows the LSU gymnastics team as they go through their season, attempting to regain their dominance in the SEC and make a deep postseason run like in the 2010s, when the Tigers advanc",
          "categories": [],
          "sportType": null,
          "competition": null,
          "imageUrl": null,
          "startAt": "2026-05-09T15:30:00Z",
          "endAt": "2026-05-09T16:00:00Z"
        },
        {
          "title": "College Lacrosse",
          "subtitle": null,
          "description": "Albany Great Danes at North Carolina Tar Heels from Dorrance Field",
          "categories": [],
          "sportType": null,
          "competition": null,
          "imageUrl": null,
          "startAt": "2026-05-09T16:00:00Z",
          "endAt": "2026-05-09T18:30:00Z"
        },
        {
          "title": "College Lacrosse",
          "subtitle": null,
          "description": "Army West Point Black Knights at Penn State Nittany Lions from Panzer Stadium",
          "categories": [],
          "sportType": null,
          "competition": null,
          "imageUrl": null,
          "startAt": "2026-05-09T18:30:00Z",
          "endAt": "2026-05-09T21:00:00Z"
        },
        {
          "title": "College Lacrosse",
          "subtitle": null,
          "description": "Johns Hopkins Blue Jays at Cornell Big Red from Schoellkopf Field",
          "categories": [],
          "sportType": null,
          "competition": null,
          "imageUrl": null,
          "startAt": "2026-05-09T21:00:00Z",
          "endAt": "2026-05-09T23:30:00Z"
        }
      ]
    },
    {
      "id": "MLBNetwork.us",
      "name": "MLB Network",
      "logoUrl": "https://i.imgur.com/sA5V39D.png",
      "provider": "TVTV US sports guide",
      "providerKey": "premium-tvtv-us",
      "sources": [
        "data/normalized/guide-premium-US-tvtv.us.xml",
        "data/normalized/guide-premium-US-tvguide.com.xml"
      ],
      "currentProgram": {
        "title": "MLB Baseball",
        "subtitle": null,
        "description": "New York Mets at Arizona Diamondbacks or Pittsburgh Pirates at San Francisco Giants",
        "categories": [],
        "sportType": "Baseball",
        "competition": "MLB",
        "imageUrl": null,
        "startAt": "2026-05-09T01:30:00Z",
        "endAt": "2026-05-09T04:30:00Z"
      },
      "programs": [
        {
          "title": "MLB Baseball",
          "subtitle": null,
          "description": "Houston Astros at Cincinnati Reds or Colorado Rockies at Philadelphia Phillies",
          "categories": [],
          "sportType": "Baseball",
          "competition": "MLB",
          "imageUrl": null,
          "startAt": "2026-05-08T22:00:00Z",
          "endAt": "2026-05-09T01:00:00Z"
        },
        {
          "title": "MLB Big Inning",
          "subtitle": null,
          "description": "Must-see action from across the MLB with live look-ins, real-time highlights and big moments from all 30 teams in Major League Baseball; includes taking fans into local broadcasts to check out some of",
          "categories": [],
          "sportType": "Baseball",
          "competition": "MLB",
          "imageUrl": null,
          "startAt": "2026-05-09T01:00:00Z",
          "endAt": "2026-05-09T01:30:00Z"
        },
        {
          "title": "MLB Baseball",
          "subtitle": null,
          "description": "New York Mets at Arizona Diamondbacks or Pittsburgh Pirates at San Francisco Giants",
          "categories": [],
          "sportType": "Baseball",
          "competition": "MLB",
          "imageUrl": null,
          "startAt": "2026-05-09T01:30:00Z",
          "endAt": "2026-05-09T04:30:00Z"
        },
        {
          "title": "Quick Pitch",
          "subtitle": null,
          "description": "Catch all the latest baseball news, scores and highlights plus your first look at upcoming matchups, all in one lightning-fast hour.",
          "categories": [
            "Sports"
          ],
          "sportType": "Baseball",
          "competition": null,
          "imageUrl": null,
          "startAt": "2026-05-09T04:30:00Z",
          "endAt": "2026-05-09T05:30:00Z"
        },
        {
          "title": "Quick Pitch",
          "subtitle": null,
          "description": "Catch all the latest baseball news, scores and highlights plus your first look at upcoming matchups, all in one lightning-fast hour.",
          "categories": [
            "Sports"
          ],
          "sportType": "Baseball",
          "competition": null,
          "imageUrl": null,
          "startAt": "2026-05-09T05:30:00Z",
          "endAt": "2026-05-09T06:30:00Z"
        },
        {
          "title": "Quick Pitch",
          "subtitle": null,
          "description": "Catch all the latest baseball news, scores and highlights plus your first look at upcoming matchups, all in one lightning-fast hour.",
          "categories": [
            "Sports"
          ],
          "sportType": "Baseball",
          "competition": null,
          "imageUrl": null,
          "startAt": "2026-05-09T06:30:00Z",
          "endAt": "2026-05-09T07:30:00Z"
        },
        {
          "title": "Quick Pitch",
          "subtitle": null,
          "description": "Catch all the latest baseball news, scores and highlights plus your first look at upcoming matchups, all in one lightning-fast hour.",
          "categories": [
            "Sports"
          ],
          "sportType": "Baseball",
          "competition": null,
          "imageUrl": null,
          "startAt": "2026-05-09T07:30:00Z",
          "endAt": "2026-05-09T08:30:00Z"
        },
        {
          "title": "Quick Pitch",
          "subtitle": null,
          "description": "Catch all the latest baseball news, scores and highlights plus your first look at upcoming matchups, all in one lightning-fast hour.",
          "categories": [
            "Sports"
          ],
          "sportType": "Baseball",
          "competition": null,
          "imageUrl": null,
          "startAt": "2026-05-09T08:30:00Z",
          "endAt": "2026-05-09T09:00:00Z"
        },
        {
          "title": "Quick Pitch",
          "subtitle": null,
          "description": "Catch all the latest baseball news, scores and highlights plus your first look at upcoming matchups, all in one lightning-fast hour.",
          "categories": [
            "Sports"
          ],
          "sportType": "Baseball",
          "competition": null,
          "imageUrl": null,
          "startAt": "2026-05-09T09:00:00Z",
          "endAt": "2026-05-09T10:00:00Z"
        },
        {
          "title": "Quick Pitch",
          "subtitle": null,
          "description": "Catch all the latest baseball news, scores and highlights plus your first look at upcoming matchups, all in one lightning-fast hour.",
          "categories": [
            "Sports"
          ],
          "sportType": "Baseball",
          "competition": null,
          "imageUrl": null,
          "startAt": "2026-05-09T10:00:00Z",
          "endAt": "2026-05-09T11:00:00Z"
        },
        {
          "title": "Quick Pitch",
          "subtitle": null,
          "description": "Catch all the latest baseball news, scores and highlights plus your first look at upcoming matchups, all in one lightning-fast hour.",
          "categories": [
            "Sports"
          ],
          "sportType": "Baseball",
          "competition": null,
          "imageUrl": null,
          "startAt": "2026-05-09T11:00:00Z",
          "endAt": "2026-05-09T12:00:00Z"
        },
        {
          "title": "Quick Pitch",
          "subtitle": null,
          "description": "Catch all the latest baseball news, scores and highlights plus your first look at upcoming matchups, all in one lightning-fast hour.",
          "categories": [
            "Sports"
          ],
          "sportType": "Baseball",
          "competition": null,
          "imageUrl": null,
          "startAt": "2026-05-09T12:00:00Z",
          "endAt": "2026-05-09T13:00:00Z"
        },
        {
          "title": "Quick Pitch",
          "subtitle": null,
          "description": "Catch all the latest baseball news, scores and highlights plus your first look at upcoming matchups, all in one lightning-fast hour.",
          "categories": [
            "Sports"
          ],
          "sportType": "Baseball",
          "competition": null,
          "imageUrl": null,
          "startAt": "2026-05-09T13:00:00Z",
          "endAt": "2026-05-09T14:00:00Z"
        },
        {
          "title": "Quick Pitch",
          "subtitle": null,
          "description": "Catch all the latest baseball news, scores and highlights plus your first look at upcoming matchups, all in one lightning-fast hour.",
          "categories": [
            "Sports"
          ],
          "sportType": "Baseball",
          "competition": null,
          "imageUrl": null,
          "startAt": "2026-05-09T14:00:00Z",
          "endAt": "2026-05-09T15:00:00Z"
        },
        {
          "title": "Quick Pitch",
          "subtitle": null,
          "description": "Catch all the latest baseball news, scores and highlights plus your first look at upcoming matchups, all in one lightning-fast hour.",
          "categories": [
            "Sports"
          ],
          "sportType": "Baseball",
          "competition": null,
          "imageUrl": null,
          "startAt": "2026-05-09T15:00:00Z",
          "endAt": "2026-05-09T16:00:00Z"
        },
        {
          "title": "Quick Pitch",
          "subtitle": null,
          "description": "Catch all the latest baseball news, scores and highlights plus your first look at upcoming matchups, all in one lightning-fast hour.",
          "categories": [
            "Sports"
          ],
          "sportType": "Baseball",
          "competition": null,
          "imageUrl": null,
          "startAt": "2026-05-09T16:00:00Z",
          "endAt": "2026-05-09T17:00:00Z"
        },
        {
          "title": "Play Ball",
          "subtitle": null,
          "description": "The host joins analysts to perform one-on-one demonstrations and show the intricacies of the game, along with interviews with some of the top players in the game and discussions on how kids can furthe",
          "categories": [],
          "sportType": null,
          "competition": null,
          "imageUrl": null,
          "startAt": "2026-05-09T17:00:00Z",
          "endAt": "2026-05-09T17:30:00Z"
        },
        {
          "title": "MLB Network Podcast",
          "subtitle": null,
          "description": "Featuring entertaining and insightful conversations with people from all over the baseball world, including Hall of Famers, current players, former All-Stars and celebrity fans",
          "categories": [],
          "sportType": "Baseball",
          "competition": "MLB",
          "imageUrl": null,
          "startAt": "2026-05-09T17:30:00Z",
          "endAt": "2026-05-09T18:00:00Z"
        },
        {
          "title": "MLB Network: Double Play",
          "subtitle": null,
          "description": "One of the most exciting recent games replayed in a fast-paced, action-filled version.",
          "categories": [],
          "sportType": "Baseball",
          "competition": "MLB",
          "imageUrl": null,
          "startAt": "2026-05-09T18:00:00Z",
          "endAt": "2026-05-09T20:00:00Z"
        },
        {
          "title": "MLB Tonight: Inside the Park",
          "subtitle": null,
          "description": null,
          "categories": [],
          "sportType": "Baseball",
          "competition": "MLB",
          "imageUrl": null,
          "startAt": "2026-05-09T20:00:00Z",
          "endAt": "2026-05-09T23:30:00Z"
        }
      ]
    },
    {
      "id": "NBATV.us",
      "name": "NBA TV",
      "logoUrl": "https://upload.wikimedia.org/wikipedia/en/thumb/d/d2/NBA_TV.svg/960px-NBA_TV.svg.png",
      "provider": "TVTV US sports guide",
      "providerKey": "premium-tvtv-us",
      "sources": [
        "data/normalized/guide-premium-US-tvtv.us.xml",
        "data/normalized/guide-premium-US-tvguide.com.xml"
      ],
      "currentProgram": {
        "title": "The Association: Postgame",
        "subtitle": null,
        "description": "Analysts recap the recent NBA game, breaking down highlights of the key moments throughout the contest, the top players who determined the outcome, and interviews with the players and coaches to hear",
        "categories": [],
        "sportType": "Basketball",
        "competition": "NBA",
        "imageUrl": null,
        "startAt": "2026-05-09T01:30:00Z",
        "endAt": "2026-05-09T02:30:00Z"
      },
      "programs": [
        {
          "title": "Chasing History",
          "subtitle": null,
          "description": null,
          "categories": [],
          "sportType": null,
          "competition": null,
          "imageUrl": null,
          "startAt": "2026-05-08T22:00:00Z",
          "endAt": "2026-05-08T22:30:00Z"
        },
        {
          "title": "NBA Playback",
          "subtitle": null,
          "description": null,
          "categories": [],
          "sportType": "Basketball",
          "competition": "NBA",
          "imageUrl": null,
          "startAt": "2026-05-08T22:30:00Z",
          "endAt": "2026-05-09T00:30:00Z"
        },
        {
          "title": "Basketcast",
          "subtitle": null,
          "description": null,
          "categories": [],
          "sportType": null,
          "competition": null,
          "imageUrl": null,
          "startAt": "2026-05-09T00:30:00Z",
          "endAt": "2026-05-09T01:30:00Z"
        },
        {
          "title": "The Association: Postgame",
          "subtitle": null,
          "description": "Analysts recap the recent NBA game, breaking down highlights of the key moments throughout the contest, the top players who determined the outcome, and interviews with the players and coaches to hear",
          "categories": [],
          "sportType": "Basketball",
          "competition": "NBA",
          "imageUrl": null,
          "startAt": "2026-05-09T01:30:00Z",
          "endAt": "2026-05-09T02:30:00Z"
        },
        {
          "title": "The Association: Postgame",
          "subtitle": null,
          "description": "Analysts recap the recent NBA game, breaking down highlights of the key moments throughout the contest, the top players who determined the outcome, and interviews with the players and coaches to hear",
          "categories": [],
          "sportType": "Basketball",
          "competition": "NBA",
          "imageUrl": null,
          "startAt": "2026-05-09T02:30:00Z",
          "endAt": "2026-05-09T03:30:00Z"
        },
        {
          "title": "The Association: Postgame",
          "subtitle": null,
          "description": "Analysts recap the recent NBA game, breaking down highlights of the key moments throughout the contest, the top players who determined the outcome, and interviews with the players and coaches to hear",
          "categories": [],
          "sportType": "Basketball",
          "competition": "NBA",
          "imageUrl": null,
          "startAt": "2026-05-09T03:30:00Z",
          "endAt": "2026-05-09T04:00:00Z"
        },
        {
          "title": "The Association: Postgame",
          "subtitle": null,
          "description": "Analysts recap the recent NBA game, breaking down highlights of the key moments throughout the contest, the top players who determined the outcome, and interviews with the players and coaches to hear",
          "categories": [],
          "sportType": "Basketball",
          "competition": "NBA",
          "imageUrl": null,
          "startAt": "2026-05-09T04:00:00Z",
          "endAt": "2026-05-09T05:00:00Z"
        },
        {
          "title": "The Association: Postgame",
          "subtitle": null,
          "description": "Analysts recap the recent NBA game, breaking down highlights of the key moments throughout the contest, the top players who determined the outcome, and interviews with the players and coaches to hear",
          "categories": [],
          "sportType": "Basketball",
          "competition": "NBA",
          "imageUrl": null,
          "startAt": "2026-05-09T05:00:00Z",
          "endAt": "2026-05-09T06:00:00Z"
        },
        {
          "title": "The Association: Post Up",
          "subtitle": null,
          "description": null,
          "categories": [],
          "sportType": null,
          "competition": null,
          "imageUrl": null,
          "startAt": "2026-05-09T06:00:00Z",
          "endAt": "2026-05-09T06:30:00Z"
        },
        {
          "title": "The Association: Post Up",
          "subtitle": null,
          "description": null,
          "categories": [],
          "sportType": null,
          "competition": null,
          "imageUrl": null,
          "startAt": "2026-05-09T06:30:00Z",
          "endAt": "2026-05-09T07:00:00Z"
        },
        {
          "title": "The Association: Post Up",
          "subtitle": null,
          "description": null,
          "categories": [],
          "sportType": null,
          "competition": null,
          "imageUrl": null,
          "startAt": "2026-05-09T07:00:00Z",
          "endAt": "2026-05-09T07:30:00Z"
        },
        {
          "title": "The Association: Post Up",
          "subtitle": null,
          "description": null,
          "categories": [],
          "sportType": null,
          "competition": null,
          "imageUrl": null,
          "startAt": "2026-05-09T07:30:00Z",
          "endAt": "2026-05-09T08:00:00Z"
        },
        {
          "title": "The Association: Post Up",
          "subtitle": null,
          "description": null,
          "categories": [],
          "sportType": null,
          "competition": null,
          "imageUrl": null,
          "startAt": "2026-05-09T08:00:00Z",
          "endAt": "2026-05-09T08:30:00Z"
        },
        {
          "title": "The Association: Post Up",
          "subtitle": null,
          "description": null,
          "categories": [],
          "sportType": null,
          "competition": null,
          "imageUrl": null,
          "startAt": "2026-05-09T08:30:00Z",
          "endAt": "2026-05-09T09:00:00Z"
        },
        {
          "title": "The Association: Post Up",
          "subtitle": null,
          "description": null,
          "categories": [],
          "sportType": null,
          "competition": null,
          "imageUrl": null,
          "startAt": "2026-05-09T09:00:00Z",
          "endAt": "2026-05-09T09:30:00Z"
        },
        {
          "title": "The Association: Post Up",
          "subtitle": null,
          "description": null,
          "categories": [],
          "sportType": null,
          "competition": null,
          "imageUrl": null,
          "startAt": "2026-05-09T09:30:00Z",
          "endAt": "2026-05-09T10:00:00Z"
        },
        {
          "title": "The Association: Post Up",
          "subtitle": null,
          "description": null,
          "categories": [],
          "sportType": null,
          "competition": null,
          "imageUrl": null,
          "startAt": "2026-05-09T10:00:00Z",
          "endAt": "2026-05-09T10:30:00Z"
        },
        {
          "title": "The Association: Post Up",
          "subtitle": null,
          "description": null,
          "categories": [],
          "sportType": null,
          "competition": null,
          "imageUrl": null,
          "startAt": "2026-05-09T10:30:00Z",
          "endAt": "2026-05-09T11:00:00Z"
        },
        {
          "title": "The Association: Post Up",
          "subtitle": null,
          "description": null,
          "categories": [],
          "sportType": null,
          "competition": null,
          "imageUrl": null,
          "startAt": "2026-05-09T11:00:00Z",
          "endAt": "2026-05-09T11:30:00Z"
        },
        {
          "title": "The Association: Post Up",
          "subtitle": null,
          "description": null,
          "categories": [],
          "sportType": null,
          "competition": null,
          "imageUrl": null,
          "startAt": "2026-05-09T11:30:00Z",
          "endAt": "2026-05-09T12:00:00Z"
        },
        {
          "title": "The Association: Post Up",
          "subtitle": null,
          "description": null,
          "categories": [],
          "sportType": null,
          "competition": null,
          "imageUrl": null,
          "startAt": "2026-05-09T12:00:00Z",
          "endAt": "2026-05-09T12:30:00Z"
        },
        {
          "title": "The Association: Post Up",
          "subtitle": null,
          "description": null,
          "categories": [],
          "sportType": null,
          "competition": null,
          "imageUrl": null,
          "startAt": "2026-05-09T12:30:00Z",
          "endAt": "2026-05-09T13:00:00Z"
        },
        {
          "title": "NBA Nightcap",
          "subtitle": null,
          "description": null,
          "categories": [],
          "sportType": "Basketball",
          "competition": "NBA",
          "imageUrl": null,
          "startAt": "2026-05-09T13:00:00Z",
          "endAt": "2026-05-09T13:30:00Z"
        },
        {
          "title": "The Association: Post Up",
          "subtitle": null,
          "description": null,
          "categories": [],
          "sportType": null,
          "competition": null,
          "imageUrl": null,
          "startAt": "2026-05-09T13:30:00Z",
          "endAt": "2026-05-09T14:00:00Z"
        },
        {
          "title": "NBA Nightcap",
          "subtitle": null,
          "description": null,
          "categories": [],
          "sportType": "Basketball",
          "competition": "NBA",
          "imageUrl": null,
          "startAt": "2026-05-09T14:00:00Z",
          "endAt": "2026-05-09T14:30:00Z"
        },
        {
          "title": "The Association: Post Up",
          "subtitle": null,
          "description": null,
          "categories": [],
          "sportType": null,
          "competition": null,
          "imageUrl": null,
          "startAt": "2026-05-09T14:30:00Z",
          "endAt": "2026-05-09T15:00:00Z"
        },
        {
          "title": "NBA Nightcap",
          "subtitle": null,
          "description": null,
          "categories": [],
          "sportType": "Basketball",
          "competition": "NBA",
          "imageUrl": null,
          "startAt": "2026-05-09T15:00:00Z",
          "endAt": "2026-05-09T15:30:00Z"
        },
        {
          "title": "The Association: Post Up",
          "subtitle": null,
          "description": null,
          "categories": [],
          "sportType": null,
          "competition": null,
          "imageUrl": null,
          "startAt": "2026-05-09T15:30:00Z",
          "endAt": "2026-05-09T16:00:00Z"
        },
        {
          "title": "NBA Playback",
          "subtitle": null,
          "description": null,
          "categories": [],
          "sportType": "Basketball",
          "competition": "NBA",
          "imageUrl": null,
          "startAt": "2026-05-09T16:00:00Z",
          "endAt": "2026-05-09T18:00:00Z"
        },
        {
          "title": "Chasing History",
          "subtitle": null,
          "description": null,
          "categories": [],
          "sportType": null,
          "competition": null,
          "imageUrl": null,
          "startAt": "2026-05-09T18:00:00Z",
          "endAt": "2026-05-09T18:30:00Z"
        },
        {
          "title": "NBA Shot Clock: Best Games of the Night",
          "subtitle": null,
          "description": null,
          "categories": [],
          "sportType": "Basketball",
          "competition": "NBA",
          "imageUrl": null,
          "startAt": "2026-05-09T18:30:00Z",
          "endAt": "2026-05-09T21:30:00Z"
        },
        {
          "title": "The Association: Postgame",
          "subtitle": null,
          "description": "Analysts recap the recent NBA game, breaking down highlights of the key moments throughout the contest, the top players who determined the outcome, and interviews with the players and coaches to hear",
          "categories": [],
          "sportType": "Basketball",
          "competition": "NBA",
          "imageUrl": null,
          "startAt": "2026-05-09T21:30:00Z",
          "endAt": "2026-05-09T22:30:00Z"
        }
      ]
    },
    {
      "id": "NFLNetwork.us",
      "name": "NFL Network",
      "logoUrl": "https://upload.wikimedia.org/wikipedia/en/thumb/8/8f/NFL_Network_logo.svg/960px-NFL_Network_logo.svg.png",
      "provider": "TVTV US sports guide",
      "providerKey": "premium-tvtv-us",
      "sources": [
        "data/normalized/guide-premium-US-tvtv.us.xml",
        "data/normalized/guide-premium-US-tvguide.com.xml"
      ],
      "currentProgram": {
        "title": "NFL Playoffs",
        "subtitle": null,
        "description": "Los Angeles Rams at Chicago Bears from Soldier Field",
        "categories": [],
        "sportType": null,
        "competition": null,
        "imageUrl": null,
        "startAt": "2026-05-09T00:00:00Z",
        "endAt": "2026-05-09T03:00:00Z"
      },
      "programs": [
        {
          "title": "A Football Life",
          "subtitle": null,
          "description": "A second-round pick in 1996, safety Brian Dawkins quickly became the leader of the Eagles defense before moving on to the Broncos for his last three years, earning five first team All-Pro nods and a P",
          "categories": [
            "Documentary",
            "Sports"
          ],
          "sportType": "Football",
          "competition": null,
          "imageUrl": null,
          "startAt": "2026-05-08T22:00:00Z",
          "endAt": "2026-05-08T23:00:00Z"
        },
        {
          "title": "The Insiders",
          "subtitle": null,
          "description": "NFL insiders, including Ian Rapoport, Tom Pelissero and Mike Garafolo, break down the latest team news making headlines across the league, discussing the impact it will have on the team, along with th",
          "categories": [],
          "sportType": null,
          "competition": null,
          "imageUrl": null,
          "startAt": "2026-05-08T23:00:00Z",
          "endAt": "2026-05-09T00:00:00Z"
        },
        {
          "title": "NFL Playoffs",
          "subtitle": null,
          "description": "Los Angeles Rams at Chicago Bears from Soldier Field",
          "categories": [],
          "sportType": null,
          "competition": null,
          "imageUrl": null,
          "startAt": "2026-05-09T00:00:00Z",
          "endAt": "2026-05-09T03:00:00Z"
        },
        {
          "title": "The Insiders",
          "subtitle": null,
          "description": "NFL insiders, including Ian Rapoport, Tom Pelissero and Mike Garafolo, break down the latest team news making headlines across the league, discussing the impact it will have on the team, along with th",
          "categories": [],
          "sportType": null,
          "competition": null,
          "imageUrl": null,
          "startAt": "2026-05-09T03:00:00Z",
          "endAt": "2026-05-09T04:00:00Z"
        },
        {
          "title": "NFL Playoffs",
          "subtitle": null,
          "description": "Houston Texans at New England Patriots from Gillette Stadium",
          "categories": [],
          "sportType": null,
          "competition": null,
          "imageUrl": null,
          "startAt": "2026-05-09T04:00:00Z",
          "endAt": "2026-05-09T07:00:00Z"
        },
        {
          "title": "NFL Playoffs",
          "subtitle": null,
          "description": "San Francisco 49ers at Seattle Seahawks from Lumen Field",
          "categories": [],
          "sportType": null,
          "competition": null,
          "imageUrl": null,
          "startAt": "2026-05-09T07:00:00Z",
          "endAt": "2026-05-09T10:00:00Z"
        },
        {
          "title": "NFL Mic'd Up",
          "subtitle": null,
          "description": "Players and coaches are wired for sound during the week's biggest games, capturing the fanfare of the crowd and the player introduction ceremonies, as well as showcasing their unique personalities on",
          "categories": [],
          "sportType": null,
          "competition": null,
          "imageUrl": null,
          "startAt": "2026-05-09T10:00:00Z",
          "endAt": "2026-05-09T10:30:00Z"
        },
        {
          "title": "NFL Playoffs",
          "subtitle": null,
          "description": "Los Angeles Chargers at New England Patriots from Gillette Stadium",
          "categories": [],
          "sportType": null,
          "competition": null,
          "imageUrl": null,
          "startAt": "2026-05-09T10:30:00Z",
          "endAt": "2026-05-09T13:00:00Z"
        },
        {
          "title": "NFL Playoffs",
          "subtitle": null,
          "description": "Los Angeles Rams at Carolina Panthers from Bank of America Stadium",
          "categories": [],
          "sportType": null,
          "competition": null,
          "imageUrl": null,
          "startAt": "2026-05-09T13:00:00Z",
          "endAt": "2026-05-09T16:00:00Z"
        },
        {
          "title": "NFL Playoffs",
          "subtitle": null,
          "description": "San Francisco 49ers at Philadelphia Eagles from Lincoln Financial Field",
          "categories": [],
          "sportType": null,
          "competition": null,
          "imageUrl": null,
          "startAt": "2026-05-09T16:00:00Z",
          "endAt": "2026-05-09T19:00:00Z"
        },
        {
          "title": "NFL Playoffs",
          "subtitle": null,
          "description": "Buffalo Bills at Jacksonville Jaguars from EverBank Stadium",
          "categories": [],
          "sportType": null,
          "competition": null,
          "imageUrl": null,
          "startAt": "2026-05-09T19:00:00Z",
          "endAt": "2026-05-09T22:00:00Z"
        },
        {
          "title": "NFL Playoffs",
          "subtitle": null,
          "description": "Green Bay Packers at Chicago Bears from Soldier Field",
          "categories": [],
          "sportType": null,
          "competition": null,
          "imageUrl": null,
          "startAt": "2026-05-09T22:00:00Z",
          "endAt": "2026-05-10T01:00:00Z"
        }
      ]
    }
  ]
}
